LICENSE
README.md
setup.py
modelagnosticsafeaipackage/__init__.py
modelagnosticsafeaipackage/check_accuracy.py
modelagnosticsafeaipackage/check_explainability.py
modelagnosticsafeaipackage/check_fairness.py
modelagnosticsafeaipackage/check_privacy.py
modelagnosticsafeaipackage/check_robustness.py
modelagnosticsafeaipackage.egg-info/PKG-INFO
modelagnosticsafeaipackage.egg-info/SOURCES.txt
modelagnosticsafeaipackage.egg-info/dependency_links.txt
modelagnosticsafeaipackage.egg-info/top_level.txt
modelagnosticsafeaipackage/utils/__init__.py
modelagnosticsafeaipackage/utils/util.py